pylshvec/__init__.py
pylshvec/lshvec.py
pylshvec/utils.py
pylshvec-0.1.dist-info/METADATA
pylshvec-0.1.dist-info/WHEEL
pylshvec-0.1.dist-info/top_level.txt
pylshvec-0.1.dist-info/RECORD
