Metadata-Version: 2.1
Name: pylshvec
Version: 0.1
Summary: LSHVec pre-trained models and its Python bindings
Home-page: https://github.com/Lizhen0909/PyLSHvec
Author: Lizhen Shi
Author-email: lizhen9.shi@gmail.com
License: UNKNOWN
Platform: UNKNOWN
Classifier: Programming Language :: Python :: 3
Classifier: License :: OSI Approved :: MIT License
Classifier: Operating System :: OS Independent
Requires-Dist: Cython (>=0.28.5)
Requires-Dist: jnius (>=1.1.0)
